setup.py
newman/__init__.py
newman/argument.py
newman/color.py
newman/core.py
newman/decorators.py
newman.egg-info/PKG-INFO
newman.egg-info/SOURCES.txt
newman.egg-info/dependency_links.txt
newman.egg-info/entry_points.txt
newman.egg-info/requires.txt
newman.egg-info/top_level.txt