Metadata-Version: 1.0
Name: newman
Version: 0.6.7
Summary: Simple utility for making command tools.  Inspired by rake.
Home-page: UNKNOWN
Author: Matt O'Donnell
Author-email: matt.odonnell@adkeeper.com
License: UNKNOWN
Platform: UNKNOWN
Classifier: Operating System :: POSIX
Classifier: Environment :: Console
